Metadata-Version: 1.1
Name: seussexport
Version: 0.4
Summary: SEU Export From Statseeker
Home-page: https://github.com/ipv6freely/seussexport
Author: Chris Jones
Author-email: ipv6freely@gmail.com
License: UNKNOWN
Download-URL: https://github.com/ipv6freely/seussexport/archive/0.4.tar.gz
Keywords: statseeker,export
Platform: UNKNOWN
